gaiacmds/__init__.py
gaiacmds/gaiacmds.py
gaiacmds-0.5.1.dist-info/licenses/LICENSE
gaiacmds-0.5.1.dist-info/METADATA
gaiacmds-0.5.1.dist-info/WHEEL
gaiacmds-0.5.1.dist-info/top_level.txt
gaiacmds-0.5.1.dist-info/RECORD
