Metadata-Version: 2.4
Name: gaiacmds
Version: 0.5.1
Summary: Good enough CMDs based on simple star cluster member selection.
Home-page: https://github.com/avapolzin/goodenough_gaia_cmds
Author: Ava Polzin
Author-email: apolzin@uchicago.edu
License: MIT
Classifier: Development Status :: 4 - Beta
Classifier: License :: OSI Approved :: MIT License
Classifier: Operating System :: OS Independent
Classifier: Programming Language :: Python
Requires-Python: >=3
License-File: LICENSE
Requires-Dist: astropy
Requires-Dist: astroquery
Requires-Dist: matplotlib
Requires-Dist: numpy
Requires-Dist: pandas
Dynamic: author
Dynamic: author-email
Dynamic: classifier
Dynamic: description
Dynamic: description-content-type
Dynamic: home-page
Dynamic: license
Dynamic: license-file
Dynamic: requires-dist
Dynamic: requires-python
Dynamic: summary
